LICENSE
MANIFEST.in
README
README.rst
setup.cfg
setup.py
examples/.DS_Store
examples/dcard_term.py
examples/get_post_content.py
examples/simple_male_female_ratio.py
pydcard/__init__.py
pydcard/api.py
pydcard/pydcard.py
pydcard.egg-info/PKG-INFO
pydcard.egg-info/SOURCES.txt
pydcard.egg-info/dependency_links.txt
pydcard.egg-info/not-zip-safe
pydcard.egg-info/requires.txt
pydcard.egg-info/top_level.txt
screenshots/.DS_Store
screenshots/dcard_term.gif