Metadata-Version: 1.1
Name: pydcard
Version: 0.0.8
Summary: This is a Dcard API wrapper
Home-page: http://github.com/John-Lin/pydcard
Author: John Lin
Author-email: linton.tw@gmail.com
License: MIT
Platform: UNKNOWN
Classifier: Development Status :: 5 - Production/Stable
Classifier: Environment :: Console
Classifier: Intended Audience :: Developers
Classifier: License :: OSI Approved :: MIT License
Classifier: Operating System :: OS Independent
Classifier: Programming Language :: Python
Classifier: Topic :: Utilities
Classifier: Topic :: Software Development :: Libraries :: Python Modules
